isaac_analyzer/__init__.py
isaac_analyzer/cli.py
isaac_analyzer/items.py
isaac_analyzer/logging.py
isaac_analyzer/plotter.py
isaac_analyzer/run_loader.py
isaac_analyzer/utils.py
isaac_analyzer/validator.py
isaac_analyzer/yaml_loader.py
isaac_analyzer/analysis/__init__.py
isaac_analyzer/analysis/boss.py
isaac_analyzer/analysis/curses.py
isaac_analyzer/analysis/deals.py
isaac_analyzer/analysis/endings.py
isaac_analyzer/analysis/items.py
isaac_analyzer/analysis/main.py
isaac_analyzer/analysis/shop.py
isaac_analyzer/plotting/__init__.py
isaac_analyzer/plotting/double_chart.py
isaac_analyzer/plotting/single_chart.py
isaac_analyzer/resources/items.yaml
isaac_analyzer/resources/run_file_schema.json
tests/__init__.py
tests/test_cli.py
tests/test_items.py
tests/test_yaml_loader.py
isaac_analyzer-0.2.14.dist-info/LICENSE
isaac_analyzer-0.2.14.dist-info/METADATA
isaac_analyzer-0.2.14.dist-info/WHEEL
isaac_analyzer-0.2.14.dist-info/entry_points.txt
isaac_analyzer-0.2.14.dist-info/top_level.txt
isaac_analyzer-0.2.14.dist-info/RECORD
