Metadata-Version: 2.1
Name: isaac-analyzer
Version: 0.2.14
Summary: A CLI application to analyze isaac runs documented in YAML
Home-page: https://git.roth-kl.de/isaac/isaac-analyzer
Author: Supporterino
Author-email: lars@roth-kl.de
Classifier: Programming Language :: Python :: 3
Classifier: License :: OSI Approved :: MIT License
Classifier: Operating System :: OS Independent
Requires-Python: >=3.9
License-File: LICENSE
Requires-Dist: pyyaml
Requires-Dist: tabulate
Requires-Dist: jsonschema
Requires-Dist: matplotlib
Requires-Dist: numpy
Requires-Dist: Pillow
